{
  "submissions": [
    {
      "id": "6f37"
    },
    {
      "id": "5459",
      "field1": "Ranjith",
      "field2": "Aravindakshan"
    },
    {
      "id": "d98e",
      "field1": "PRabhu",
      "field2": "krsihnan"
    },
    {
      "id": "2580",
      "ProductName": "Ranjith",
      "Description": "43242",
      "category": "electronics",
      "retailprice": "344",
      "retailcurrency": "USD",
      "wholesaleprice": "34141",
      "wholesalecurrency": "USD",
      "stock": "141"
    },
    {
      "id": "3de5",
      "ProductName": "Ranjith",
      "Description": "43242",
      "category": "electronics",
      "retailprice": "344",
      "retailcurrency": "USD",
      "wholesaleprice": "34141",
      "wholesalecurrency": "USD",
      "stock": "141"
    },
    {
      "id": "f8d1",
      "ProductName": "Ranjith",
      "Description": "43242",
      "category": "electronics",
      "retailprice": "344",
      "retailcurrency": "USD",
      "wholesaleprice": "34141",
      "wholesalecurrency": "USD",
      "stock": "141"
    },
    {
      "id": "dc3e",
      "ProductName": "Ranjith",
      "Description": "43242",
      "category": "electronics",
      "retailprice": "344",
      "retailcurrency": "USD",
      "wholesaleprice": "34141",
      "wholesalecurrency": "USD",
      "stock": "141"
    },
    {
      "id": "b406",
      "ProductName": "Ranjith",
      "Description": "1313231",
      "category": "electronics",
      "retailprice": "44",
      "retailcurrency": "USD",
      "wholesaleprice": "44",
      "wholesalecurrency": "USD",
      "stock": "3"
    },
    {
      "id": "3f74",
      "ProductName": "Ranjith",
      "Description": "1313231",
      "category": "electronics",
      "retailprice": "44",
      "retailcurrency": "USD",
      "wholesaleprice": "44",
      "wholesalecurrency": "USD",
      "stock": "3"
    },
    {
      "id": "2d61",
      "ProductName": "Ranjith",
      "Description": "1313231",
      "category": "electronics",
      "retailprice": "44",
      "retailcurrency": "USD",
      "wholesaleprice": "44",
      "wholesalecurrency": "USD",
      "stock": "3"
    },
    {
      "id": "f64c",
      "ProductName": "Ranjith",
      "Description": "000",
      "category": "electronics",
      "retailprice": "88",
      "retailcurrency": "USD",
      "wholesaleprice": "99",
      "wholesalecurrency": "USD",
      "stock": "000"
    },
    {
      "id": "270c",
      "ProductName": "Ranjith",
      "Description": "45",
      "category": "electronics",
      "retailprice": "42342",
      "retailcurrency": "USD",
      "wholesaleprice": "313",
      "wholesalecurrency": "USD",
      "stock": "231"
    },
    {
      "id": "50da",
      "ProductName": "Ranjith",
      "Description": "Testing",
      "category": "1001",
      "retailprice": "33",
      "retailcurrency": "USD",
      "wholesaleprice": "333",
      "wholesalecurrency": "USD",
      "stock": "333"
    },
    {
      "id": "eafd",
      "ProductName": "Ranjith",
      "Description": "YYY",
      "category": "1001",
      "retailprice": "33",
      "retailcurrency": "USD",
      "wholesaleprice": "333",
      "wholesalecurrency": "USD",
      "stock": "333"
    },
    {
      "id": "b308",
      "ProductName": "Ranjith",
      "Description": "Teee",
      "category": "1001",
      "retailprice": "33",
      "retailcurrency": "USD",
      "wholesaleprice": "333",
      "wholesalecurrency": "USD",
      "stock": "333"
    },
    {
      "id": "32ed",
      "productName": "ewqeq",
      "description": "weweq",
      "category": "1001",
      "retailPrice": "33",
      "retailCurrency": "USD",
      "wholesalePrice": "333",
      "wholeSaleCurrency": "USD",
      "quantity": "33"
    },
    {
      "id": "5134",
      "productName": "RANJITH",
      "description": "R",
      "category": "1001",
      "retailPrice": "10",
      "retailCurrency": "USD",
      "wholesalePrice": "10",
      "wholeSaleCurrency": "USD",
      "quantity": "1"
    },
    {
      "id": "81eb",
      "productName": "RANJITH",
      "description": "Tet",
      "category": "1001",
      "retailPrice": "10",
      "retailCurrency": "USD",
      "wholesalePrice": "10",
      "wholeSaleCurrency": "USD",
      "quantity": "1"
    },
    {
      "id": "72ec",
      "productName": "RANJITH",
      "description": "Test",
      "category": "1001",
      "retailPrice": "10",
      "retailCurrency": "USD",
      "wholesalePrice": "10",
      "wholeSaleCurrency": "USD",
      "quantity": "1"
    },
    {
      "id": "5a90",
      "productName": "RANJITH",
      "description": "Ra",
      "category": "1001",
      "retailPrice": "10",
      "retailCurrency": "USD",
      "wholesalePrice": "10",
      "wholeSaleCurrency": "USD",
      "quantity": "1"
    },
    {
      "id": "07f2",
      "productName": "RANJITH",
      "description": "Ra",
      "category": "1001",
      "retailPrice": "10",
      "retailCurrency": "USD",
      "wholesalePrice": "10",
      "wholeSaleCurrency": "USD",
      "quantity": "1"
    },
    {
      "id": "cdde",
      "productName": "RANJITH",
      "description": "Ra",
      "category": "1001",
      "retailPrice": "10",
      "retailCurrency": "USD",
      "wholesalePrice": "10",
      "wholeSaleCurrency": "USD",
      "quantity": "1"
    },
    {
      "id": "4709",
      "productName": "RANJITH",
      "description": "Ra",
      "category": "1001",
      "retailPrice": "10",
      "retailCurrency": "USD",
      "wholesalePrice": "10",
      "wholeSaleCurrency": "USD",
      "quantity": "1"
    }
  ]
}